{
    "0xD49F9B0955C367DE": {
        "name": "CREATE_PED",
        "jhash": "0x0389EF71",
        "comment": "https://alloc8or.re/gta5/doc/enums/ePedType.txt\n\nFull list of peds by DurtyFree: https://github.com/DurtyFree/gta-v-data-dumps/blob/master/peds.json",
        "params": [
            {
                "type": "int",
                "name": "pedType"
            },
            {
                "type": "Hash",
                "name": "modelHash"
            },
            {
                "type": "float",
                "name": "x"
            },
            {
                "type": "float",
                "name": "y"
            },
            {
                "type": "float",
                "name": "z"
            },
            {
                "type": "float",
                "name": "heading"
            },
            {
                "type": "BOOL",
                "name": "isNetwork"
            },
            {
                "type": "BOOL",
                "name": "bScriptHostPed"
            }
        ],
        "return_type": "Ped",
        "build": "323"
    }
}